xchainpy2_thorchain/__init__.py
xchainpy2_thorchain/client.py
xchainpy2_thorchain/const.py
xchainpy2_thorchain/memo.py
xchainpy2_thorchain/models.py
xchainpy2_thorchain/utils.py
xchainpy2_thorchain/proto/__init__.py
xchainpy2_thorchain/proto/cosmos/__init__.py
xchainpy2_thorchain/proto/cosmos/base/__init__.py
xchainpy2_thorchain/proto/cosmos/base/v1beta1/__init__.py
xchainpy2_thorchain/proto/cosmos/base/v1beta1/coin_pb2.py
xchainpy2_thorchain/proto/cosmos/base/v1beta1/coin_pb2.pyi
xchainpy2_thorchain/proto/cosmos/base/v1beta1/coin_pb2_grpc.py
xchainpy2_thorchain/proto/gogoproto/__init__.py
xchainpy2_thorchain/proto/gogoproto/gogo_pb2.py
xchainpy2_thorchain/proto/gogoproto/gogo_pb2.pyi
xchainpy2_thorchain/proto/gogoproto/gogo_pb2_grpc.py
xchainpy2_thorchain/proto/thorchain/__init__.py
xchainpy2_thorchain/proto/thorchain/v1/__init__.py
xchainpy2_thorchain/proto/thorchain/v1/common/__init__.py
xchainpy2_thorchain/proto/thorchain/v1/common/common_pb2.py
xchainpy2_thorchain/proto/thorchain/v1/common/common_pb2.pyi
xchainpy2_thorchain/proto/thorchain/v1/common/common_pb2_grpc.py
xchainpy2_thorchain/proto/thorchain/v1/x/__init__.py
xchainpy2_thorchain/proto/thorchain/v1/x/thorchain/__init__.py
xchainpy2_thorchain/proto/thorchain/v1/x/thorchain/types/__init__.py
xchainpy2_thorchain/proto/thorchain/v1/x/thorchain/types/msg_deposit_pb2.py
xchainpy2_thorchain/proto/thorchain/v1/x/thorchain/types/msg_deposit_pb2.pyi
xchainpy2_thorchain/proto/thorchain/v1/x/thorchain/types/msg_deposit_pb2_grpc.py
xchainpy2_thorchain/proto/thorchain/v1/x/thorchain/types/msg_send_pb2.py
xchainpy2_thorchain/proto/thorchain/v1/x/thorchain/types/msg_send_pb2.pyi
xchainpy2_thorchain/proto/thorchain/v1/x/thorchain/types/msg_send_pb2_grpc.py
xchainpy2_thorchain/tests/__init__.py
xchainpy2_thorchain/tests/test_basic_tc.py
xchainpy2_thorchain/tests/test_fee.py
xchainpy2_thorchain/tests/test_memo.py
xchainpy2_thorchain/tests/test_utils.py
xchainpy2_thorchain/tests/mock/network.json
xchainpy2_thorchain-0.0.35.dist-info/licenses/LICENSE
xchainpy2_thorchain-0.0.35.dist-info/METADATA
xchainpy2_thorchain-0.0.35.dist-info/WHEEL
xchainpy2_thorchain-0.0.35.dist-info/top_level.txt
xchainpy2_thorchain-0.0.35.dist-info/RECORD
